profile_profile_local/__init__.py
profile_profile_local/profile_profile.py
profile_profile_local-0.0.20.dist-info/METADATA
profile_profile_local-0.0.20.dist-info/WHEEL
profile_profile_local-0.0.20.dist-info/top_level.txt
profile_profile_local-0.0.20.dist-info/RECORD
