Metadata-Version: 2.1
Name: profile-profile-local
Version: 0.0.20
Summary: PyPI Package for Circles profile-profile-local Python
Home-page: https://github.com/circles-zone/profile-profile-local-python-package
Author: Circles
Author-email: info@circlez.ai
Classifier: Programming Language :: Python :: 3
Classifier: License :: Other/Proprietary License
Classifier: Operating System :: OS Independent
Requires-Dist: logger-local >=0.0.71
Requires-Dist: database-mysql-local >=0.0.120
